im_futuretest_webapp2/__init__.py
im_futuretest_webapp2-0.1.1.dist-info/DESCRIPTION.rst
im_futuretest_webapp2-0.1.1.dist-info/METADATA
im_futuretest_webapp2-0.1.1.dist-info/RECORD
im_futuretest_webapp2-0.1.1.dist-info/WHEEL
im_futuretest_webapp2-0.1.1.dist-info/metadata.json
im_futuretest_webapp2-0.1.1.dist-info/top_level.txt
