Metadata-Version: 2.0
Name: im-futuretest-webapp2
Version: 0.1.1
Summary: webapp2 handlers and route utils for im_futuretask, for Google App Engine, Python standard environment
Home-page: https://github.com/emlynoregan/im_futuretest_webapp2
Author: Emlyn O'Regan
Author-email: emlynoregan@gmail.com
License: ../LICENSE.txt
Platform: UNKNOWN
Classifier: Development Status :: 3 - Alpha
Classifier: Intended Audience :: Developers
Classifier: License :: OSI Approved :: Apache Software License
Classifier: Operating System :: POSIX
Classifier: Operating System :: Microsoft :: Windows
Classifier: Operating System :: MacOS :: MacOS X
Classifier: Programming Language :: Python :: 2.7
Classifier: Programming Language :: Python :: Implementation :: CPython
Classifier: Topic :: Software Development :: Libraries :: Python Modules
Classifier: Topic :: System :: Distributed Computing
Requires-Dist: im-futuretest (>=0.1.4)
